tablesage/__init__.py
tablesage/base_task.py
tablesage/column_annotator.py
tablesage/column_summarizer.py
tablesage/insights_extractor.py
tablesage/properties_comparer.py
tablesage/properties_fuser.py
tablesage/properties_merger.py
tablesage/semantic_types.py
tablesage/spatial_extractor.py
tablesage/table_annotator.py
tablesage/table_summarizer.py
tablesage/table_task.py
tablesage/tablesage.py
tablesage/temporal_extractor.py
tablesage/text_task.py
tablesage-0.0.8.dist-info/LICENSE
tablesage-0.0.8.dist-info/METADATA
tablesage-0.0.8.dist-info/WHEEL
tablesage-0.0.8.dist-info/top_level.txt
tablesage-0.0.8.dist-info/RECORD
