Metadata-Version: 2.1
Name: tablesage
Version: 0.0.8
Summary: A profiling tool for tabular data leveraging the powerful capabilities of LLMs, appropriate for data scientists.
Author-email: Alexandros Zeakis <azeakis@athenarc.gr>
Project-URL: Homepage, https://github.com/stelar-eu/TableSage
Classifier: License :: OSI Approved :: Apache Software License
Classifier: Programming Language :: Python
Requires-Python: >=3.6
License-File: LICENSE
Requires-Dist: openai==1.57.4
Requires-Dist: pandas==2.2.3
